rt2/__init__.py
rt2/model.py
rt2-0.1.0.dist-info/LICENSE
rt2-0.1.0.dist-info/WHEEL
rt2-0.1.0.dist-info/METADATA
rt2-0.1.0.dist-info/RECORD
