Metadata-Version: 2.1
Name: rt2
Version: 0.1.0
Summary: rt-2 - PyTorch
Home-page: https://github.com/kyegomez/rt-2
License: MIT
Keywords: artificial intelligence,deep learning,optimizers,Prompt Engineering
Author: Kye Gomez
Author-email: kye@apac.ai
Requires-Python: >=3.6,<4.0
Classifier: Development Status :: 4 - Beta
Classifier: Intended Audience :: Developers
Classifier: License :: OSI Approved :: MIT License
Classifier: Programming Language :: Python :: 3
Classifier: Programming Language :: Python :: 3.6
Classifier: Programming Language :: Python :: 3.7
Classifier: Programming Language :: Python :: 3.8
Classifier: Programming Language :: Python :: 3.9
Classifier: Programming Language :: Python :: 3.10
Classifier: Programming Language :: Python :: 3.11
Classifier: Programming Language :: Python :: 3.6
Classifier: Topic :: Scientific/Engineering :: Artificial Intelligence
Requires-Dist: beartype
Requires-Dist: classifier-free-guidance-pytorch
Requires-Dist: einops
Requires-Dist: palm-rlhf-pytorch
Requires-Dist: palme
Requires-Dist: tokenizers
Requires-Dist: torch
Requires-Dist: transformers
Requires-Dist: wandb
Requires-Dist: zetascale
Project-URL: Documentation, https://github.com/kyegomez/rt-2
Project-URL: Repository, https://github.com/kyegomez/rt-2
